[
  {
    "start_date": "2026-04-28",
    "end_date": "2026-05-01",
    "nights": 3,
    "month_bucket": "Abril",
    "p25": 48.89,
    "p50": 54.77,
    "p75": 57.42,
    "f_gap": 0.9,
    "f_leadtime": 0.8,
    "f_pace": 1.0,
    "raw_price": 39.43,
    "recommended_price": 48.89,
    "min_price": 48.89,
    "max_price": 56.89,
    "weekly_price_after_discount_5pct": null,
    "refundable_price": 44.0,
    "strategy": "agresiva",
    "review_date_30d": null,
    "review_date_15d": null,
    "review_date_7d": null,
    "next_action": "Hueco cercano; revisar a diario"
  },
  {
    "start_date": "2026-05-19",
    "end_date": "2026-05-20",
    "nights": 1,
    "month_bucket": "Mayo",
    "p25": 56.48,
    "p50": 58.94,
    "p75": 60.25,
    "f_gap": 0.65,
    "f_leadtime": 0.95,
    "f_pace": 1.0,
    "raw_price": 36.4,
    "recommended_price": 50.83,
    "min_price": 50.83,
    "max_price": 58.83,
    "weekly_price_after_discount_5pct": null,
    "refundable_price": 45.75,
    "strategy": "agresiva",
    "review_date_30d": null,
    "review_date_15d": "2026-05-04",
    "review_date_7d": "2026-05-12",
    "next_action": "Revisar el 2026-05-04; si no se vende, bajar 5–10%"
  },
  {
    "start_date": "2026-05-30",
    "end_date": "2026-06-01",
    "nights": 2,
    "month_bucket": "Mayo",
    "p25": 56.48,
    "p50": 58.94,
    "p75": 60.25,
    "f_gap": 0.8,
    "f_leadtime": 1.0,
    "f_pace": 1.0,
    "raw_price": 47.15,
    "recommended_price": 56.48,
    "min_price": 56.48,
    "max_price": 58.94,
    "weekly_price_after_discount_5pct": null,
    "refundable_price": 50.83,
    "strategy": "agresiva",
    "review_date_30d": "2026-04-30",
    "review_date_15d": "2026-05-15",
    "review_date_7d": "2026-05-23",
    "next_action": "Revisar el 2026-04-30; si no se vende, bajar 5%"
  },
  {
    "start_date": "2026-06-28",
    "end_date": "2026-06-30",
    "nights": 2,
    "month_bucket": "Junio",
    "p25": 75.11,
    "p50": 78.67,
    "p75": 82.33,
    "f_gap": 0.8,
    "f_leadtime": 1.05,
    "f_pace": 1.0,
    "raw_price": 66.08,
    "recommended_price": 75.11,
    "min_price": 75.11,
    "max_price": 78.67,
    "weekly_price_after_discount_5pct": null,
    "refundable_price": 67.6,
    "strategy": "agresiva",
    "review_date_30d": "2026-05-29",
    "review_date_15d": "2026-06-13",
    "review_date_7d": "2026-06-21",
    "next_action": "Revisar el 2026-05-29; si no se vende, bajar 5%"
  },
  {
    "start_date": "2026-07-10",
    "end_date": "2026-07-12",
    "nights": 2,
    "month_bucket": "Julio",
    "p25": 91.5,
    "p50": 99.33,
    "p75": 105.0,
    "f_gap": 0.8,
    "f_leadtime": 1.05,
    "f_pace": 1.0,
    "raw_price": 83.44,
    "recommended_price": 91.5,
    "min_price": 91.5,
    "max_price": 99.33,
    "weekly_price_after_discount_5pct": null,
    "refundable_price": 82.35,
    "strategy": "agresiva",
    "review_date_30d": "2026-06-10",
    "review_date_15d": "2026-06-25",
    "review_date_7d": "2026-07-03",
    "next_action": "Revisar el 2026-06-10; si no se vende, bajar 5%"
  },
  {
    "start_date": "2026-07-17",
    "end_date": "2026-07-21",
    "nights": 4,
    "month_bucket": "Julio",
    "p25": 91.5,
    "p50": 99.33,
    "p75": 105.0,
    "f_gap": 0.95,
    "f_leadtime": 1.05,
    "f_pace": 1.0,
    "raw_price": 99.08,
    "recommended_price": 99.08,
    "min_price": 94.08,
    "max_price": 105.0,
    "weekly_price_after_discount_5pct": null,
    "refundable_price": 89.17,
    "strategy": "equilibrada",
    "review_date_30d": "2026-06-17",
    "review_date_15d": "2026-07-02",
    "review_date_7d": "2026-07-10",
    "next_action": "Revisar el 2026-06-17; si no se vende, bajar 5%"
  },
  {
    "start_date": "2026-07-28",
    "end_date": "2026-07-30",
    "nights": 2,
    "month_bucket": "Julio",
    "p25": 91.5,
    "p50": 99.33,
    "p75": 105.0,
    "f_gap": 0.8,
    "f_leadtime": 1.05,
    "f_pace": 1.0,
    "raw_price": 83.44,
    "recommended_price": 91.5,
    "min_price": 91.5,
    "max_price": 99.33,
    "weekly_price_after_discount_5pct": null,
    "refundable_price": 82.35,
    "strategy": "agresiva",
    "review_date_30d": "2026-06-28",
    "review_date_15d": "2026-07-13",
    "review_date_7d": "2026-07-21",
    "next_action": "Revisar el 2026-06-28; si no se vende, bajar 5%"
  },
  {
    "start_date": "2026-08-14",
    "end_date": "2026-08-18",
    "nights": 4,
    "month_bucket": "Agosto",
    "p25": 93.75,
    "p50": 99.0,
    "p75": 105.0,
    "f_gap": 0.95,
    "f_leadtime": 1.05,
    "f_pace": 1.0,
    "raw_price": 98.75,
    "recommended_price": 98.75,
    "min_price": 93.75,
    "max_price": 105.0,
    "weekly_price_after_discount_5pct": null,
    "refundable_price": 88.88,
    "strategy": "equilibrada",
    "review_date_30d": "2026-07-15",
    "review_date_15d": "2026-07-30",
    "review_date_7d": "2026-08-07",
    "next_action": "Revisar el 2026-07-15; si no se vende, bajar 5%"
  },
  {
    "start_date": "2026-08-28",
    "end_date": "2026-08-30",
    "nights": 2,
    "month_bucket": "Agosto",
    "p25": 93.75,
    "p50": 99.0,
    "p75": 105.0,
    "f_gap": 0.8,
    "f_leadtime": 1.05,
    "f_pace": 1.0,
    "raw_price": 83.16,
    "recommended_price": 93.75,
    "min_price": 93.75,
    "max_price": 99.0,
    "weekly_price_after_discount_5pct": null,
    "refundable_price": 84.38,
    "strategy": "agresiva",
    "review_date_30d": "2026-07-29",
    "review_date_15d": "2026-08-13",
    "review_date_7d": "2026-08-21",
    "next_action": "Revisar el 2026-07-29; si no se vende, bajar 5%"
  },
  {
    "start_date": "2026-09-14",
    "end_date": "2026-09-16",
    "nights": 2,
    "month_bucket": "Septiembre",
    "p25": 74.92,
    "p50": 85.0,
    "p75": 92.97,
    "f_gap": 0.8,
    "f_leadtime": 1.05,
    "f_pace": 1.0,
    "raw_price": 71.4,
    "recommended_price": 74.92,
    "min_price": 74.92,
    "max_price": 82.92,
    "weekly_price_after_discount_5pct": null,
    "refundable_price": 67.43,
    "strategy": "agresiva",
    "review_date_30d": "2026-08-15",
    "review_date_15d": "2026-08-30",
    "review_date_7d": "2026-09-07",
    "next_action": "Revisar el 2026-08-15; si no se vende, bajar 5%"
  },
  {
    "start_date": "2026-10-02",
    "end_date": "2026-10-04",
    "nights": 2,
    "month_bucket": "Octubre",
    "p25": 52.08,
    "p50": 60.1,
    "p75": 66.44,
    "f_gap": 0.8,
    "f_leadtime": 1.05,
    "f_pace": 1.0,
    "raw_price": 50.48,
    "recommended_price": 52.08,
    "min_price": 52.08,
    "max_price": 60.08,
    "weekly_price_after_discount_5pct": null,
    "refundable_price": 46.87,
    "strategy": "agresiva",
    "review_date_30d": "2026-09-02",
    "review_date_15d": "2026-09-17",
    "review_date_7d": "2026-09-25",
    "next_action": "Revisar el 2026-09-02; si no se vende, bajar 5%"
  },
  {
    "start_date": "2026-10-12",
    "end_date": "2026-10-26",
    "nights": 14,
    "month_bucket": "Octubre",
    "p25": 52.08,
    "p50": 60.1,
    "p75": 66.44,
    "f_gap": 1.0,
    "f_leadtime": 1.05,
    "f_pace": 1.0,
    "raw_price": 63.11,
    "recommended_price": 63.11,
    "min_price": 58.11,
    "max_price": 66.44,
    "weekly_price_after_discount_5pct": 419.68,
    "refundable_price": 56.8,
    "strategy": "equilibrada",
    "review_date_30d": "2026-09-12",
    "review_date_15d": "2026-09-27",
    "review_date_7d": "2026-10-05",
    "next_action": "Revisar el 2026-09-12; si no se vende, bajar 5%"
  },
  {
    "start_date": "2026-11-01",
    "end_date": "2026-12-23",
    "nights": 52,
    "month_bucket": "Noviembre",
    "p25": 43.9,
    "p50": 47.75,
    "p75": 50.0,
    "f_gap": 1.0,
    "f_leadtime": 1.05,
    "f_pace": 1.0,
    "raw_price": 50.14,
    "recommended_price": 50.0,
    "min_price": 45.0,
    "max_price": 50.0,
    "weekly_price_after_discount_5pct": 332.5,
    "refundable_price": 45.0,
    "strategy": "premium",
    "review_date_30d": "2026-10-02",
    "review_date_15d": "2026-10-17",
    "review_date_7d": "2026-10-25",
    "next_action": "Revisar el 2026-10-02; si no se vende, bajar 5%"
  }
]